Workbook

Sheet HOW TO USE
B2: Succession Planning Toolkit
B3: Strategnosis Solutions OPC — free edition
B5: What this workbook does
B6: It takes you from a list of positions to a defensible answer for two questions: which roles would hurt most if they emptied tomorrow, and who is actually ready to step into them.
B8: Fill the sheets in this order
B9: 1. LIST OF POSITIONS | C9: Replace the sample plantilla with your own positions and salary grades.
B10: 2. SUCCESSION PLANNING | C10: For each position: headcount, vacancies, and the three criticality factors. Criticality level is computed.
B11: 3. SUCCESSOR ASSESSMENT MATRIX | C11: Name candidates against a target position and rate them 1–4 on seven criteria. Match % and readiness are computed.
B12: 4. SUCCESSION BENCH | C12: Nothing to fill in. Depth and strength count themselves from the matrix.
B13: 5. COMPETENCY POSITION PROFILE | C13: Optional. Required vs assessed competency levels for one position at a time.
B15: Which cells to type in
B16: Yellow fill, blue text | C16: Type here. These are your inputs.
B17: White fill, black text | C17: Computed by formula. Typing over these breaks the sheet.
B18: CONFIG sheet | C18: Scoring thresholds. Change them there and every sheet follows.
B20: Sample data
B21: Row 2 of SUCCESSION PLANNING and the first three rows of the assessment matrix are filled with example values so you can see the scoring work end to end. Clear them before entering real data.
B24: Where the thresholds came from
B25: Readiness bands (100% / 80% / 50%) are the ones defined in the source template. The criticality bands on CONFIG are a starting point, not a standard — expect to lower them once you can see how your own scores distribute. Ready Now at 100% requires a perfect rating on all seven criteria, so an empty Ready Now column early on is the definition working as written, not a mistake.
B28: Questions about applying this to your organization: strategnosissolutions@gmail.com

Sheet CONFIG
B2: SCORING CONFIGURATION
B3: Criticality scoring | C3: Value | D3: Note
B4: Number of criticality factors | C4: 3 | D4: Revenue generating, risk exposure, specialization.
B5: Maximum rating per factor | C5: 5 | D5: Each factor is rated 1–5.
B6: Maximum possible criticality score | C6: =C4*C5 | D6: Computed. Used only as a reference for setting the bands below.
B7: Highly Critical — minimum score | C7: 13 | D7: Very high organizational impact and replacement difficulty.
B8: Critical — minimum score | C8: 10 | D8: Significant operational or strategic importance.
B9: Moderately Critical — minimum score | C9: 7 | D9: Anything below this scores as Noncritical.
B11: Successor readiness | C11: Value | D11: Note
B12: Number of successor criteria | C12: 7 | D12: Qualification standards through degree of likability.
B13: Maximum rating per criterion | C13: 4 | D13: Each criterion is rated 1–4.
B14: Maximum possible points | C14: =C12*C13 | D14: Computed. The denominator behind every Overall Match percentage.
B15: Ready Now — minimum match | C15: 1 | D15: Match All. A perfect rating on every criterion.
B16: Ready Soon — minimum match | C16: 0.8 | D16: Match Most. Short-term development, under 2 years.
B17: Ready Later — minimum match | C17: 0.5 | D17: Match Some. Long-term development, 3 years or more.
B19: Anything below the Ready Later floor is classed Not Ready — a gap that cannot presently be closed through development.

Sheet LIST OF POSITIONS
B1: Position | C1: SG
B2: Executive Director | C2: 28
B3: Deputy Executive Director | C3: 27
B4: Department Manager III | C4: 26
B5: Legal Officer V | C5: 25
B6: Chief Administrative Officer | C6: 24
B7: Chief Information Officer | C7: 24
B8: Internal Auditor V | C8: 24
B9: Planning Officer V | C9: 24
B10: Legal Officer IV | C10: 23
B11: Division Chief | C11: 22
B12: Information Technology Officer II | C12: 22
B13: Internal Auditor IV | C13: 22
... B39: Administrative Aide I (Utility Worker I) | C39: 1

Sheet DEFINITION OF TERMS
A1: Term | B1: Definition
A2: Approved Position | B2: Authorized plantilla position approved for the organization.
A3: Approved Positions (Based on Plantilla) | B3: Total number of authorized positions under the approved plantilla.
A4: Available Workforce (Filled Positions) | B4: Number of plantilla positions currently occupied by employees.
A5: Existing Vacancies | B5: Positions currently vacant and available for hiring or appointment.
A6: Potential Vacancies | B6: Positions projected to become vacant due to retirement, promotion, transfer, resignation, study leave, non-renewal of contract, or other workforce movements.
A7: Total Vacancy | B7: Combined total of existing and potential vacancies.
A8: Performance Trend | B8: General performance rating trend of incumbents occupying the position.
A9: O (Outstanding) | B9: Highest level of performance, consistently exceeding expected standards.
A10: VS (Very Satisfactory) | B10: Performance frequently exceeds expected standards.
A11: S (Satisfactory) | B11: Performance meets expected standards.
A12: US (Unsatisfactory) | B12: Performance does not meet expected standards.
... A38: Strength | B38: Number of successor candidates assessed as Ready Now.

Sheet SUCCESSION PLANNING
A1: # | B1: Approved Position | C1: Approved Positions (Plantilla) | D1: Available Workforce (Filled) | E1: Existing Vacancies | F1: Potential Vacancies | G1: Total Vacancy | H1: Performance Trend | I1: Competency Level | J1: Revenue Generating | K1: Risk Exposure | L1: Specialization | M1: Total Criticality Score | N1: Critical Position Level | O1: Criteria / Remarks
A2: =ROW()-1 | B2: =IF('LIST OF POSITIONS'!B2="","",'LIST OF POSITIONS'!B2) | C2: 1 | D2: 1 | E2: =IF(OR(C2="",D2=""),"",C2-D2) | F2: 1 | G2: =IF(AND(E2="",F2=""),"",N(E2)+N(F2)) | H2: VS | I2: Meeting | J2: 5 | K2: 5 | L2: 4 | M2: =IF(COUNT(J2:L2)=0,"",SUM(J2:L2)) | N2: =IF(M2="","",IF(M2>=CONFIG!$C$7,"Highly Critical",IF(M2>=CONFIG!$C$8,"Critical",IF(M2>=CONFIG!$C$9,"Moderately Critical","Noncritical")))) | O2: EXAMPLE ROW — incumbent retires in 14 months. Clear before entering your own data.
A3: =ROW()-1 | B3: =IF('LIST OF POSITIONS'!B3="","",'LIST OF POSITIONS'!B3) | E3: =IF(OR(C3="",D3=""),"",C3-D3) | G3: =IF(AND(E3="",F3=""),"",N(E3)+N(F3)) | M3: =IF(COUNT(J3:L3)=0,"",SUM(J3:L3)) | N3: =IF(M3="","",IF(M3>=CONFIG!$C$7,"Highly Critical",IF(M3>=CONFIG!$C$8,"Critical",IF(M3>=CONFIG!$C$9,"Moderately Critical","Noncritical"))))
A4: =ROW()-1 | B4: =IF('LIST OF POSITIONS'!B4="","",'LIST OF POSITIONS'!B4) | E4: =IF(OR(C4="",D4=""),"",C4-D4) | G4: =IF(AND(E4="",F4=""),"",N(E4)+N(F4)) | M4: =IF(COUNT(J4:L4)=0,"",SUM(J4:L4)) | N4: =IF(M4="","",IF(M4>=CONFIG!$C$7,"Highly Critical",IF(M4>=CONFIG!$C$8,"Critical",IF(M4>=CONFIG!$C$9,"Moderately Critical","Noncritical"))))
A5: =ROW()-1 | B5: =IF('LIST OF POSITIONS'!B5="","",'LIST OF POSITIONS'!B5) | E5: =IF(OR(C5="",D5=""),"",C5-D5) | G5: =IF(AND(E5="",F5=""),"",N(E5)+N(F5)) | M5: =IF(COUNT(J5:L5)=0,"",SUM(J5:L5)) | N5: =IF(M5="","",IF(M5>=CONFIG!$C$7,"Highly Critical",IF(M5>=CONFIG!$C$8,"Critical",IF(M5>=CONFIG!$C$9,"Moderately Critical","Noncritical"))))
A6: =ROW()-1 | B6: =IF('LIST OF POSITIONS'!B6="","",'LIST OF POSITIONS'!B6) | E6: =IF(OR(C6="",D6=""),"",C6-D6) | G6: =IF(AND(E6="",F6=""),"",N(E6)+N(F6)) | M6: =IF(COUNT(J6:L6)=0,"",SUM(J6:L6)) | N6: =IF(M6="","",IF(M6>=CONFIG!$C$7,"Highly Critical",IF(M6>=CONFIG!$C$8,"Critical",IF(M6>=CONFIG!$C$9,"Moderately Critical","Noncritical"))))
A7: =ROW()-1 | B7: =IF('LIST OF POSITIONS'!B7="","",'LIST OF POSITIONS'!B7) | E7: =IF(OR(C7="",D7=""),"",C7-D7) | G7: =IF(AND(E7="",F7=""),"",N(E7)+N(F7)) | M7: =IF(COUNT(J7:L7)=0,"",SUM(J7:L7)) | N7: =IF(M7="","",IF(M7>=CONFIG!$C$7,"Highly Critical",IF(M7>=CONFIG!$C$8,"Critical",IF(M7>=CONFIG!$C$9,"Moderately Critical","Noncritical"))))
A8: =ROW()-1 | B8: =IF('LIST OF POSITIONS'!B8="","",'LIST OF POSITIONS'!B8) | E8: =IF(OR(C8="",D8=""),"",C8-D8) | G8: =IF(AND(E8="",F8=""),"",N(E8)+N(F8)) | M8: =IF(COUNT(J8:L8)=0,"",SUM(J8:L8)) | N8: =IF(M8="","",IF(M8>=CONFIG!$C$7,"Highly Critical",IF(M8>=CONFIG!$C$8,"Critical",IF(M8>=CONFIG!$C$9,"Moderately Critical","Noncritical"))))
A9: =ROW()-1 | B9: =IF('LIST OF POSITIONS'!B9="","",'LIST OF POSITIONS'!B9) | E9: =IF(OR(C9="",D9=""),"",C9-D9) | G9: =IF(AND(E9="",F9=""),"",N(E9)+N(F9)) | M9: =IF(COUNT(J9:L9)=0,"",SUM(J9:L9)) | N9: =IF(M9="","",IF(M9>=CONFIG!$C$7,"Highly Critical",IF(M9>=CONFIG!$C$8,"Critical",IF(M9>=CONFIG!$C$9,"Moderately Critical","Noncritical"))))
A10: =ROW()-1 | B10: =IF('LIST OF POSITIONS'!B10="","",'LIST OF POSITIONS'!B10) | E10: =IF(OR(C10="",D10=""),"",C10-D10) | G10: =IF(AND(E10="",F10=""),"",N(E10)+N(F10)) | M10: =IF(COUNT(J10:L10)=0,"",SUM(J10:L10)) | N10: =IF(M10="","",IF(M10>=CONFIG!$C$7,"Highly Critical",IF(M10>=CONFIG!$C$8,"Critical",IF(M10>=CONFIG!$C$9,"Moderately Critical","Noncritical"))))
A11: =ROW()-1 | B11: =IF('LIST OF POSITIONS'!B11="","",'LIST OF POSITIONS'!B11) | E11: =IF(OR(C11="",D11=""),"",C11-D11) | G11: =IF(AND(E11="",F11=""),"",N(E11)+N(F11)) | M11: =IF(COUNT(J11:L11)=0,"",SUM(J11:L11)) | N11: =IF(M11="","",IF(M11>=CONFIG!$C$7,"Highly Critical",IF(M11>=CONFIG!$C$8,"Critical",IF(M11>=CONFIG!$C$9,"Moderately Critical","Noncritical"))))
A12: =ROW()-1 | B12: =IF('LIST OF POSITIONS'!B12="","",'LIST OF POSITIONS'!B12) | E12: =IF(OR(C12="",D12=""),"",C12-D12) | G12: =IF(AND(E12="",F12=""),"",N(E12)+N(F12)) | M12: =IF(COUNT(J12:L12)=0,"",SUM(J12:L12)) | N12: =IF(M12="","",IF(M12>=CONFIG!$C$7,"Highly Critical",IF(M12>=CONFIG!$C$8,"Critical",IF(M12>=CONFIG!$C$9,"Moderately Critical","Noncritical"))))
A13: =ROW()-1 | B13: =IF('LIST OF POSITIONS'!B13="","",'LIST OF POSITIONS'!B13) | E13: =IF(OR(C13="",D13=""),"",C13-D13) | G13: =IF(AND(E13="",F13=""),"",N(E13)+N(F13)) | M13: =IF(COUNT(J13:L13)=0,"",SUM(J13:L13)) | N13: =IF(M13="","",IF(M13>=CONFIG!$C$7,"Highly Critical",IF(M13>=CONFIG!$C$8,"Critical",IF(M13>=CONFIG!$C$9,"Moderately Critical","Noncritical"))))
A14: =ROW()-1 | B14: =IF('LIST OF POSITIONS'!B14="","",'LIST OF POSITIONS'!B14) | E14: =IF(OR(C14="",D14=""),"",C14-D14) | G14: =IF(AND(E14="",F14=""),"",N(E14)+N(F14)) | M14: =IF(COUNT(J14:L14)=0,"",SUM(J14:L14)) | N14: =IF(M14="","",IF(M14>=CONFIG!$C$7,"Highly Critical",IF(M14>=CONFIG!$C$8,"Critical",IF(M14>=CONFIG!$C$9,"Moderately Critical","Noncritical"))))
... A39: =ROW()-1 | B39: =IF('LIST OF POSITIONS'!B39="","",'LIST OF POSITIONS'!B39) | E39: =IF(OR(C39="",D39=""),"",C39-D39) | G39: =IF(AND(E39="",F39=""),"",N(E39)+N(F39)) | M39: =IF(COUNT(J39:L39)=0,"",SUM(J39:L39)) | N39: =IF(M39="","",IF(M39>=CONFIG!$C$7,"Highly Critical",IF(M39>=CONFIG!$C$8,"Critical",IF(M39>=CONFIG!$C$9,"Moderately Critical","Noncritical"))))
B40: TOTAL | C40: =SUM(C2:C39) | D40: =SUM(D2:D39) | E40: =SUM(E2:E39) | F40: =SUM(F2:F39) | G40: =SUM(G2:G39)
B42: Highly Critical positions | C42: =COUNTIF(N2:N39,"Highly Critical")
B43: Critical positions | C43: =COUNTIF(N2:N39,"Critical")

Sheet SUCCESSOR ASSESSMENT MATRIX
A1: Target Position | B1: Potential Successor | C1: Qualification Standards | D1: Competencies | E1: Performance | F1: Learning Agility | G1: Commitment to Work | H1: Loyalty | I1: Degree of Likability | J1: Overall Match | K1: Readiness Status
A2: Executive Director | B2: A. Dela Cruz (example) | C2: 4 | D2: 4 | E2: 4 | F2: 4 | G2: 4 | H2: 4 | I2: 4 | J2: =IF(COUNT(C2:I2)=0,"",SUM(C2:I2)/CONFIG!$C$14) | K2: =IF(J2="","",IF(J2>=CONFIG!$C$15,"Ready Now",IF(J2>=CONFIG!$C$16,"Ready Soon",IF(J2>=CONFIG!$C$17,"Ready Later","Not Ready"))))
A3: Executive Director | B3: B. Santos (example) | C3: 4 | D3: 3 | E3: 4 | F3: 4 | G3: 3 | H3: 4 | I3: 3 | J3: =IF(COUNT(C3:I3)=0,"",SUM(C3:I3)/CONFIG!$C$14) | K3: =IF(J3="","",IF(J3>=CONFIG!$C$15,"Ready Now",IF(J3>=CONFIG!$C$16,"Ready Soon",IF(J3>=CONFIG!$C$17,"Ready Later","Not Ready"))))
A4: Executive Director | B4: C. Reyes (example) | C4: 3 | D4: 2 | E4: 3 | F4: 2 | G4: 3 | H4: 3 | I4: 2 | J4: =IF(COUNT(C4:I4)=0,"",SUM(C4:I4)/CONFIG!$C$14) | K4: =IF(J4="","",IF(J4>=CONFIG!$C$15,"Ready Now",IF(J4>=CONFIG!$C$16,"Ready Soon",IF(J4>=CONFIG!$C$17,"Ready Later","Not Ready"))))
J5: =IF(COUNT(C5:I5)=0,"",SUM(C5:I5)/CONFIG!$C$14) | K5: =IF(J5="","",IF(J5>=CONFIG!$C$15,"Ready Now",IF(J5>=CONFIG!$C$16,"Ready Soon",IF(J5>=CONFIG!$C$17,"Ready Later","Not Ready"))))
J6: =IF(COUNT(C6:I6)=0,"",SUM(C6:I6)/CONFIG!$C$14) | K6: =IF(J6="","",IF(J6>=CONFIG!$C$15,"Ready Now",IF(J6>=CONFIG!$C$16,"Ready Soon",IF(J6>=CONFIG!$C$17,"Ready Later","Not Ready"))))
J7: =IF(COUNT(C7:I7)=0,"",SUM(C7:I7)/CONFIG!$C$14) | K7: =IF(J7="","",IF(J7>=CONFIG!$C$15,"Ready Now",IF(J7>=CONFIG!$C$16,"Ready Soon",IF(J7>=CONFIG!$C$17,"Ready Later","Not Ready"))))
J8: =IF(COUNT(C8:I8)=0,"",SUM(C8:I8)/CONFIG!$C$14) | K8: =IF(J8="","",IF(J8>=CONFIG!$C$15,"Ready Now",IF(J8>=CONFIG!$C$16,"Ready Soon",IF(J8>=CONFIG!$C$17,"Ready Later","Not Ready"))))
J9: =IF(COUNT(C9:I9)=0,"",SUM(C9:I9)/CONFIG!$C$14) | K9: =IF(J9="","",IF(J9>=CONFIG!$C$15,"Ready Now",IF(J9>=CONFIG!$C$16,"Ready Soon",IF(J9>=CONFIG!$C$17,"Ready Later","Not Ready"))))
J10: =IF(COUNT(C10:I10)=0,"",SUM(C10:I10)/CONFIG!$C$14) | K10: =IF(J10="","",IF(J10>=CONFIG!$C$15,"Ready Now",IF(J10>=CONFIG!$C$16,"Ready Soon",IF(J10>=CONFIG!$C$17,"Ready Later","Not Ready"))))
J11: =IF(COUNT(C11:I11)=0,"",SUM(C11:I11)/CONFIG!$C$14) | K11: =IF(J11="","",IF(J11>=CONFIG!$C$15,"Ready Now",IF(J11>=CONFIG!$C$16,"Ready Soon",IF(J11>=CONFIG!$C$17,"Ready Later","Not Ready"))))
J12: =IF(COUNT(C12:I12)=0,"",SUM(C12:I12)/CONFIG!$C$14) | K12: =IF(J12="","",IF(J12>=CONFIG!$C$15,"Ready Now",IF(J12>=CONFIG!$C$16,"Ready Soon",IF(J12>=CONFIG!$C$17,"Ready Later","Not Ready"))))
J13: =IF(COUNT(C13:I13)=0,"",SUM(C13:I13)/CONFIG!$C$14) | K13: =IF(J13="","",IF(J13>=CONFIG!$C$15,"Ready Now",IF(J13>=CONFIG!$C$16,"Ready Soon",IF(J13>=CONFIG!$C$17,"Ready Later","Not Ready"))))
J14: =IF(COUNT(C14:I14)=0,"",SUM(C14:I14)/CONFIG!$C$14) | K14: =IF(J14="","",IF(J14>=CONFIG!$C$15,"Ready Now",IF(J14>=CONFIG!$C$16,"Ready Soon",IF(J14>=CONFIG!$C$17,"Ready Later","Not Ready"))))
J15: =IF(COUNT(C15:I15)=0,"",SUM(C15:I15)/CONFIG!$C$14) | K15: =IF(J15="","",IF(J15>=CONFIG!$C$15,"Ready Now",IF(J15>=CONFIG!$C$16,"Ready Soon",IF(J15>=CONFIG!$C$17,"Ready Later","Not Ready"))))
J16: =IF(COUNT(C16:I16)=0,"",SUM(C16:I16)/CONFIG!$C$14) | K16: =IF(J16="","",IF(J16>=CONFIG!$C$15,"Ready Now",IF(J16>=CONFIG!$C$16,"Ready Soon",IF(J16>=CONFIG!$C$17,"Ready Later","Not Ready"))))
... J61: =IF(COUNT(C61:I61)=0,"",SUM(C61:I61)/CONFIG!$C$14) | K61: =IF(J61="","",IF(J61>=CONFIG!$C$15,"Ready Now",IF(J61>=CONFIG!$C$16,"Ready Soon",IF(J61>=CONFIG!$C$17,"Ready Later","Not Ready"))))
A63: RATING SCALE
A64: Qualification Standards | B64: 1 — Meets none | D64: 2 — Meets some | F64: 3 — Meets most | H64: 4 — Meets all
A65: Competencies | B65: 1 — Meets none | D65: 2 — Meets 50% | F65: 3 — Meets 75% | H65: 4 — Meets all or exceeds
A66: Performance | B66: 1 — Not a high performer | D66: 2 — High performer, 1 period | F66: 3 — High performer, 2 periods | H66: 4 — High performer, 4 periods
A67: Learning Agility | B67: 1 — Resistant to learning | D67: 2 — Learns with difficulty | F67: 3 — Learns adequately | H67: 4 — Learns quickly, adapts well
A68: Commitment to Work | B68: 1 — Frequently disengaged | D68: 2 — Minimum duties only | F68: 3 — Demonstrates commitment | H68: 4 — Highly committed, exceeds
A69: Loyalty | B69: 1 — High level of disloyalty | D69: 2 — Some disloyalty | F69: 3 — Some loyalty | H69: 4 — High level of loyalty
A70: Degree of Likability | B70: 1 — Not likable | D70: 2 — Somewhat not likable | F70: 3 — Somewhat likable | H70: 4 — Very likable
A72: Loyalty and degree of likability are the two criteria hardest to defend if a promotion decision is ever contested. Record in writing why a rating was given on either before it counts toward a readiness band.

Sheet SUCCESSION BENCH
A1: Position | B1: Ready Now | C1: Ready Soon | D1: Ready Later | E1: Not Ready | F1: Depth | G1: Strength | H1: Bench Risk
A2: =IF('LIST OF POSITIONS'!B2="","",'LIST OF POSITIONS'!B2) | B2: =IF($A2="","",COUNTIFS('SUCCESSOR ASSESSMENT MATRIX'!$A$2:$A$61,$A2,'SUCCESSOR ASSESSMENT MATRIX'!$K$2:$K$61,"Ready Now")) | C2: =IF($A2="","",COUNTIFS('SUCCESSOR ASSESSMENT MATRIX'!$A$2:$A$61,$A2,'SUCCESSOR ASSESSMENT MATRIX'!$K$2:$K$61,"Ready Soon")) | D2: =IF($A2="","",COUNTIFS('SUCCESSOR ASSESSMENT MATRIX'!$A$2:$A$61,$A2,'SUCCESSOR ASSESSMENT MATRIX'!$K$2:$K$61,"Ready Later")) | E2: =IF($A2="","",COUNTIFS('SUCCESSOR ASSESSMENT MATRIX'!$A$2:$A$61,$A2,'SUCCESSOR ASSESSMENT MATRIX'!$K$2:$K$61,"Not Ready")) | F2: =IF($A2="","",SUM(B2:D2)) | G2: =IF($A2="","",B2) | H2: =IF($A2="","",IF(AND(OR('SUCCESSION PLANNING'!N2="Highly Critical",'SUCCESSION PLANNING'!N2="Critical"),F2=0),"Critical role, no bench",IF(F2=0,"No successors identified",IF(G2=0,"No one ready now","Covered"))))
A3: =IF('LIST OF POSITIONS'!B3="","",'LIST OF POSITIONS'!B3) | B3: =IF($A3="","",COUNTIFS('SUCCESSOR ASSESSMENT MATRIX'!$A$2:$A$61,$A3,'SUCCESSOR ASSESSMENT MATRIX'!$K$2:$K$61,"Ready Now")) | C3: =IF($A3="","",COUNTIFS('SUCCESSOR ASSESSMENT MATRIX'!$A$2:$A$61,$A3,'SUCCESSOR ASSESSMENT MATRIX'!$K$2:$K$61,"Ready Soon")) | D3: =IF($A3="","",COUNTIFS('SUCCESSOR ASSESSMENT MATRIX'!$A$2:$A$61,$A3,'SUCCESSOR ASSESSMENT MATRIX'!$K$2:$K$61,"Ready Later")) | E3: =IF($A3="","",COUNTIFS('SUCCESSOR ASSESSMENT MATRIX'!$A$2:$A$61,$A3,'SUCCESSOR ASSESSMENT MATRIX'!$K$2:$K$61,"Not Ready")) | F3: =IF($A3="","",SUM(B3:D3)) | G3: =IF($A3="","",B3) | H3: =IF($A3="","",IF(AND(OR('SUCCESSION PLANNING'!N3="Highly Critical",'SUCCESSION PLANNING'!N3="Critical"),F3=0),"Critical role, no bench",IF(F3=0,"No successors identified",IF(G3=0,"No one ready now","Covered"))))
A4: =IF('LIST OF POSITIONS'!B4="","",'LIST OF POSITIONS'!B4) | B4: =IF($A4="","",COUNTIFS('SUCCESSOR ASSESSMENT MATRIX'!$A$2:$A$61,$A4,'SUCCESSOR ASSESSMENT MATRIX'!$K$2:$K$61,"Ready Now")) | C4: =IF($A4="","",COUNTIFS('SUCCESSOR ASSESSMENT MATRIX'!$A$2:$A$61,$A4,'SUCCESSOR ASSESSMENT MATRIX'!$K$2:$K$61,"Ready Soon")) | D4: =IF($A4="","",COUNTIFS('SUCCESSOR ASSESSMENT MATRIX'!$A$2:$A$61,$A4,'SUCCESSOR ASSESSMENT MATRIX'!$K$2:$K$61,"Ready Later")) | E4: =IF($A4="","",COUNTIFS('SUCCESSOR ASSESSMENT MATRIX'!$A$2:$A$61,$A4,'SUCCESSOR ASSESSMENT MATRIX'!$K$2:$K$61,"Not Ready")) | F4: =IF($A4="","",SUM(B4:D4)) | G4: =IF($A4="","",B4) | H4: =IF($A4="","",IF(AND(OR('SUCCESSION PLANNING'!N4="Highly Critical",'SUCCESSION PLANNING'!N4="Critical"),F4=0),"Critical role, no bench",IF(F4=0,"No successors identified",IF(G4=0,"No one ready now","Covered"))))
A5: =IF('LIST OF POSITIONS'!B5="","",'LIST OF POSITIONS'!B5) | B5: =IF($A5="","",COUNTIFS('SUCCESSOR ASSESSMENT MATRIX'!$A$2:$A$61,$A5,'SUCCESSOR ASSESSMENT MATRIX'!$K$2:$K$61,"Ready Now")) | C5: =IF($A5="","",COUNTIFS('SUCCESSOR ASSESSMENT MATRIX'!$A$2:$A$61,$A5,'SUCCESSOR ASSESSMENT MATRIX'!$K$2:$K$61,"Ready Soon")) | D5: =IF($A5="","",COUNTIFS('SUCCESSOR ASSESSMENT MATRIX'!$A$2:$A$61,$A5,'SUCCESSOR ASSESSMENT MATRIX'!$K$2:$K$61,"Ready Later")) | E5: =IF($A5="","",COUNTIFS('SUCCESSOR ASSESSMENT MATRIX'!$A$2:$A$61,$A5,'SUCCESSOR ASSESSMENT MATRIX'!$K$2:$K$61,"Not Ready")) | F5: =IF($A5="","",SUM(B5:D5)) | G5: =IF($A5="","",B5) | H5: =IF($A5="","",IF(AND(OR('SUCCESSION PLANNING'!N5="Highly Critical",'SUCCESSION PLANNING'!N5="Critical"),F5=0),"Critical role, no bench",IF(F5=0,"No successors identified",IF(G5=0,"No one ready now","Covered"))))
A6: =IF('LIST OF POSITIONS'!B6="","",'LIST OF POSITIONS'!B6) | B6: =IF($A6="","",COUNTIFS('SUCCESSOR ASSESSMENT MATRIX'!$A$2:$A$61,$A6,'SUCCESSOR ASSESSMENT MATRIX'!$K$2:$K$61,"Ready Now")) | C6: =IF($A6="","",COUNTIFS('SUCCESSOR ASSESSMENT MATRIX'!$A$2:$A$61,$A6,'SUCCESSOR ASSESSMENT MATRIX'!$K$2:$K$61,"Ready Soon")) | D6: =IF($A6="","",COUNTIFS('SUCCESSOR ASSESSMENT MATRIX'!$A$2:$A$61,$A6,'SUCCESSOR ASSESSMENT MATRIX'!$K$2:$K$61,"Ready Later")) | E6: =IF($A6="","",COUNTIFS('SUCCESSOR ASSESSMENT MATRIX'!$A$2:$A$61,$A6,'SUCCESSOR ASSESSMENT MATRIX'!$K$2:$K$61,"Not Ready")) | F6: =IF($A6="","",SUM(B6:D6)) | G6: =IF($A6="","",B6) | H6: =IF($A6="","",IF(AND(OR('SUCCESSION PLANNING'!N6="Highly Critical",'SUCCESSION PLANNING'!N6="Critical"),F6=0),"Critical role, no bench",IF(F6=0,"No successors identified",IF(G6=0,"No one ready now","Covered"))))
A7: =IF('LIST OF POSITIONS'!B7="","",'LIST OF POSITIONS'!B7) | B7: =IF($A7="","",COUNTIFS('SUCCESSOR ASSESSMENT MATRIX'!$A$2:$A$61,$A7,'SUCCESSOR ASSESSMENT MATRIX'!$K$2:$K$61,"Ready Now")) | C7: =IF($A7="","",COUNTIFS('SUCCESSOR ASSESSMENT MATRIX'!$A$2:$A$61,$A7,'SUCCESSOR ASSESSMENT MATRIX'!$K$2:$K$61,"Ready Soon")) | D7: =IF($A7="","",COUNTIFS('SUCCESSOR ASSESSMENT MATRIX'!$A$2:$A$61,$A7,'SUCCESSOR ASSESSMENT MATRIX'!$K$2:$K$61,"Ready Later")) | E7: =IF($A7="","",COUNTIFS('SUCCESSOR ASSESSMENT MATRIX'!$A$2:$A$61,$A7,'SUCCESSOR ASSESSMENT MATRIX'!$K$2:$K$61,"Not Ready")) | F7: =IF($A7="","",SUM(B7:D7)) | G7: =IF($A7="","",B7) | H7: =IF($A7="","",IF(AND(OR('SUCCESSION PLANNING'!N7="Highly Critical",'SUCCESSION PLANNING'!N7="Critical"),F7=0),"Critical role, no bench",IF(F7=0,"No successors identified",IF(G7=0,"No one ready now","Covered"))))
A8: =IF('LIST OF POSITIONS'!B8="","",'LIST OF POSITIONS'!B8) | B8: =IF($A8="","",COUNTIFS('SUCCESSOR ASSESSMENT MATRIX'!$A$2:$A$61,$A8,'SUCCESSOR ASSESSMENT MATRIX'!$K$2:$K$61,"Ready Now")) | C8: =IF($A8="","",COUNTIFS('SUCCESSOR ASSESSMENT MATRIX'!$A$2:$A$61,$A8,'SUCCESSOR ASSESSMENT MATRIX'!$K$2:$K$61,"Ready Soon")) | D8: =IF($A8="","",COUNTIFS('SUCCESSOR ASSESSMENT MATRIX'!$A$2:$A$61,$A8,'SUCCESSOR ASSESSMENT MATRIX'!$K$2:$K$61,"Ready Later")) | E8: =IF($A8="","",COUNTIFS('SUCCESSOR ASSESSMENT MATRIX'!$A$2:$A$61,$A8,'SUCCESSOR ASSESSMENT MATRIX'!$K$2:$K$61,"Not Ready")) | F8: =IF($A8="","",SUM(B8:D8)) | G8: =IF($A8="","",B8) | H8: =IF($A8="","",IF(AND(OR('SUCCESSION PLANNING'!N8="Highly Critical",'SUCCESSION PLANNING'!N8="Critical"),F8=0),"Critical role, no bench",IF(F8=0,"No successors identified",IF(G8=0,"No one ready now","Covered"))))
A9: =IF('LIST OF POSITIONS'!B9="","",'LIST OF POSITIONS'!B9) | B9: =IF($A9="","",COUNTIFS('SUCCESSOR ASSESSMENT MATRIX'!$A$2:$A$61,$A9,'SUCCESSOR ASSESSMENT MATRIX'!$K$2:$K$61,"Ready Now")) | C9: =IF($A9="","",COUNTIFS('SUCCESSOR ASSESSMENT MATRIX'!$A$2:$A$61,$A9,'SUCCESSOR ASSESSMENT MATRIX'!$K$2:$K$61,"Ready Soon")) | D9: =IF($A9="","",COUNTIFS('SUCCESSOR ASSESSMENT MATRIX'!$A$2:$A$61,$A9,'SUCCESSOR ASSESSMENT MATRIX'!$K$2:$K$61,"Ready Later")) | E9: =IF($A9="","",COUNTIFS('SUCCESSOR ASSESSMENT MATRIX'!$A$2:$A$61,$A9,'SUCCESSOR ASSESSMENT MATRIX'!$K$2:$K$61,"Not Ready")) | F9: =IF($A9="","",SUM(B9:D9)) | G9: =IF($A9="","",B9) | H9: =IF($A9="","",IF(AND(OR('SUCCESSION PLANNING'!N9="Highly Critical",'SUCCESSION PLANNING'!N9="Critical"),F9=0),"Critical role, no bench",IF(F9=0,"No successors identified",IF(G9=0,"No one ready now","Covered"))))
A10: =IF('LIST OF POSITIONS'!B10="","",'LIST OF POSITIONS'!B10) | B10: =IF($A10="","",COUNTIFS('SUCCESSOR ASSESSMENT MATRIX'!$A$2:$A$61,$A10,'SUCCESSOR ASSESSMENT MATRIX'!$K$2:$K$61,"Ready Now")) | C10: =IF($A10="","",COUNTIFS('SUCCESSOR ASSESSMENT MATRIX'!$A$2:$A$61,$A10,'SUCCESSOR ASSESSMENT MATRIX'!$K$2:$K$61,"Ready Soon")) | D10: =IF($A10="","",COUNTIFS('SUCCESSOR ASSESSMENT MATRIX'!$A$2:$A$61,$A10,'SUCCESSOR ASSESSMENT MATRIX'!$K$2:$K$61,"Ready Later")) | E10: =IF($A10="","",COUNTIFS('SUCCESSOR ASSESSMENT MATRIX'!$A$2:$A$61,$A10,'SUCCESSOR ASSESSMENT MATRIX'!$K$2:$K$61,"Not Ready")) | F10: =IF($A10="","",SUM(B10:D10)) | G10: =IF($A10="","",B10) | H10: =IF($A10="","",IF(AND(OR('SUCCESSION PLANNING'!N10="Highly Critical",'SUCCESSION PLANNING'!N10="Critical"),F10=0),"Critical role, no bench",IF(F10=0,"No successors identified",IF(G10=0,"No one ready now","Covered"))))
A11: =IF('LIST OF POSITIONS'!B11="","",'LIST OF POSITIONS'!B11) | B11: =IF($A11="","",COUNTIFS('SUCCESSOR ASSESSMENT MATRIX'!$A$2:$A$61,$A11,'SUCCESSOR ASSESSMENT MATRIX'!$K$2:$K$61,"Ready Now")) | C11: =IF($A11="","",COUNTIFS('SUCCESSOR ASSESSMENT MATRIX'!$A$2:$A$61,$A11,'SUCCESSOR ASSESSMENT MATRIX'!$K$2:$K$61,"Ready Soon")) | D11: =IF($A11="","",COUNTIFS('SUCCESSOR ASSESSMENT MATRIX'!$A$2:$A$61,$A11,'SUCCESSOR ASSESSMENT MATRIX'!$K$2:$K$61,"Ready Later")) | E11: =IF($A11="","",COUNTIFS('SUCCESSOR ASSESSMENT MATRIX'!$A$2:$A$61,$A11,'SUCCESSOR ASSESSMENT MATRIX'!$K$2:$K$61,"Not Ready")) | F11: =IF($A11="","",SUM(B11:D11)) | G11: =IF($A11="","",B11) | H11: =IF($A11="","",IF(AND(OR('SUCCESSION PLANNING'!N11="Highly Critical",'SUCCESSION PLANNING'!N11="Critical"),F11=0),"Critical role, no bench",IF(F11=0,"No successors identified",IF(G11=0,"No one ready now","Covered"))))
A12: =IF('LIST OF POSITIONS'!B12="","",'LIST OF POSITIONS'!B12) | B12: =IF($A12="","",COUNTIFS('SUCCESSOR ASSESSMENT MATRIX'!$A$2:$A$61,$A12,'SUCCESSOR ASSESSMENT MATRIX'!$K$2:$K$61,"Ready Now")) | C12: =IF($A12="","",COUNTIFS('SUCCESSOR ASSESSMENT MATRIX'!$A$2:$A$61,$A12,'SUCCESSOR ASSESSMENT MATRIX'!$K$2:$K$61,"Ready Soon")) | D12: =IF($A12="","",COUNTIFS('SUCCESSOR ASSESSMENT MATRIX'!$A$2:$A$61,$A12,'SUCCESSOR ASSESSMENT MATRIX'!$K$2:$K$61,"Ready Later")) | E12: =IF($A12="","",COUNTIFS('SUCCESSOR ASSESSMENT MATRIX'!$A$2:$A$61,$A12,'SUCCESSOR ASSESSMENT MATRIX'!$K$2:$K$61,"Not Ready")) | F12: =IF($A12="","",SUM(B12:D12)) | G12: =IF($A12="","",B12) | H12: =IF($A12="","",IF(AND(OR('SUCCESSION PLANNING'!N12="Highly Critical",'SUCCESSION PLANNING'!N12="Critical"),F12=0),"Critical role, no bench",IF(F12=0,"No successors identified",IF(G12=0,"No one ready now","Covered"))))
A13: =IF('LIST OF POSITIONS'!B13="","",'LIST OF POSITIONS'!B13) | B13: =IF($A13="","",COUNTIFS('SUCCESSOR ASSESSMENT MATRIX'!$A$2:$A$61,$A13,'SUCCESSOR ASSESSMENT MATRIX'!$K$2:$K$61,"Ready Now")) | C13: =IF($A13="","",COUNTIFS('SUCCESSOR ASSESSMENT MATRIX'!$A$2:$A$61,$A13,'SUCCESSOR ASSESSMENT MATRIX'!$K$2:$K$61,"Ready Soon")) | D13: =IF($A13="","",COUNTIFS('SUCCESSOR ASSESSMENT MATRIX'!$A$2:$A$61,$A13,'SUCCESSOR ASSESSMENT MATRIX'!$K$2:$K$61,"Ready Later")) | E13: =IF($A13="","",COUNTIFS('SUCCESSOR ASSESSMENT MATRIX'!$A$2:$A$61,$A13,'SUCCESSOR ASSESSMENT MATRIX'!$K$2:$K$61,"Not Ready")) | F13: =IF($A13="","",SUM(B13:D13)) | G13: =IF($A13="","",B13) | H13: =IF($A13="","",IF(AND(OR('SUCCESSION PLANNING'!N13="Highly Critical",'SUCCESSION PLANNING'!N13="Critical"),F13=0),"Critical role, no bench",IF(F13=0,"No successors identified",IF(G13=0,"No one ready now","Covered"))))
... A39: =IF('LIST OF POSITIONS'!B39="","",'LIST OF POSITIONS'!B39) | B39: =IF($A39="","",COUNTIFS('SUCCESSOR ASSESSMENT MATRIX'!$A$2:$A$61,$A39,'SUCCESSOR ASSESSMENT MATRIX'!$K$2:$K$61,"Ready Now")) | C39: =IF($A39="","",COUNTIFS('SUCCESSOR ASSESSMENT MATRIX'!$A$2:$A$61,$A39,'SUCCESSOR ASSESSMENT MATRIX'!$K$2:$K$61,"Ready Soon")) | D39: =IF($A39="","",COUNTIFS('SUCCESSOR ASSESSMENT MATRIX'!$A$2:$A$61,$A39,'SUCCESSOR ASSESSMENT MATRIX'!$K$2:$K$61,"Ready Later")) | E39: =IF($A39="","",COUNTIFS('SUCCESSOR ASSESSMENT MATRIX'!$A$2:$A$61,$A39,'SUCCESSOR ASSESSMENT MATRIX'!$K$2:$K$61,"Not Ready")) | F39: =IF($A39="","",SUM(B39:D39)) | G39: =IF($A39="","",B39) | H39: =IF($A39="","",IF(AND(OR('SUCCESSION PLANNING'!N39="Highly Critical",'SUCCESSION PLANNING'!N39="Critical"),F39=0),"Critical role, no bench",IF(F39=0,"No successors identified",IF(G39=0,"No one ready now","Covered"))))
A40: TOTAL | B40: =SUM(B2:B39) | C40: =SUM(C2:C39) | D40: =SUM(D2:D39) | E40: =SUM(E2:E39) | F40: =SUM(F2:F39) | G40: =SUM(G2:G39)
A42: BENCH INTERPRETATION
A43: Depth | B43: Total viable successors — Ready Now, Ready Soon, and Ready Later combined.
A44: Strength | B44: Successors assessed as Ready Now.
A45: Critical role, no bench | B45: A position scored Critical or Highly Critical with no viable successor at all. This is the row that should start the conversation.

Sheet COMPETENCY POSITION PROFILE
A1: POSITION NAME
A2: SALARY GRADE
A4: Code | B4: Competency | C4: Required Level | D4: Assessed Rating | E4: Gap | F4: Status
A5: C1 | B5: Delivering Service Excellence | E5: =IF(OR(C5="",D5=""),"",D5-C5) | F5: =IF(E5="","",IF(E5>=0,"Meets","Below"))
A6: C2 | B6: Exemplifying Integrity | E6: =IF(OR(C6="",D6=""),"",D6-C6) | F6: =IF(E6="","",IF(E6>=0,"Meets","Below"))
A7: C3 | B7: Solving Problems and Making Decisions | E7: =IF(OR(C7="",D7=""),"",D7-C7) | F7: =IF(E7="","",IF(E7>=0,"Meets","Below"))
A8: C4 | B8: Demonstrating Personal Effectiveness | E8: =IF(OR(C8="",D8=""),"",D8-C8) | F8: =IF(E8="","",IF(E8>=0,"Meets","Below"))
A9: C5 | B9: Speaking Effectively | E9: =IF(OR(C9="",D9=""),"",D9-C9) | F9: =IF(E9="","",IF(E9>=0,"Meets","Below"))
A10: C6 | B10: Writing Effectively | E10: =IF(OR(C10="",D10=""),"",D10-C10) | F10: =IF(E10="","",IF(E10>=0,"Meets","Below"))
A11: C7 | B11: Championing and Applying Innovation | E11: =IF(OR(C11="",D11=""),"",D11-C11) | F11: =IF(E11="","",IF(E11>=0,"Meets","Below"))
A12: L1 | B12: Leading People | E12: =IF(OR(C12="",D12=""),"",D12-C12) | F12: =IF(E12="","",IF(E12>=0,"Meets","Below"))
A13: L2 | B13: Building Collaborative Networks | E13: =IF(OR(C13="",D13=""),"",D13-C13) | F13: =IF(E13="","",IF(E13>=0,"Meets","Below"))
A14: L3 | B14: Managing Performance and Coaching for Results | E14: =IF(OR(C14="",D14=""),"",D14-C14) | F14: =IF(E14="","",IF(E14>=0,"Meets","Below"))
A15: L4 | B15: Thinking Strategically and Creatively | E15: =IF(OR(C15="",D15=""),"",D15-C15) | F15: =IF(E15="","",IF(E15>=0,"Meets","Below"))
A16: L5 | B16: Creating and Nurturing a High-Performing Organization | E16: =IF(OR(C16="",D16=""),"",D16-C16) | F16: =IF(E16="","",IF(E16>=0,"Meets","Below"))
... A24: F8 | B24: Procurement and Supply Management | E24: =IF(OR(C24="",D24=""),"",D24-C24) | F24: =IF(E24="","",IF(E24>=0,"Meets","Below"))
B26: Competencies assessed | C26: =COUNT(D5:D24)
B27: Meeting the required level | C27: =COUNTIF(F5:F24,"Meets")
B28: Profile match | C28: =IFERROR(C27/C26,"")
B30: A negative gap is the development agenda: it names the competency, the size of the shortfall, and therefore what training would actually change the readiness band on the assessment matrix.
